AUTHORS
LICENSE
MANIFEST.in
README.md
setup.py
zinnia_foundation/__init__.py
zinnia_foundation/static/zinnia/css/foundation.css
zinnia_foundation/static/zinnia/css/foundation.min.css
zinnia_foundation/static/zinnia/css/normalize.css
zinnia_foundation/static/zinnia/icons/.fontcustom-data
zinnia_foundation/static/zinnia/icons/foundation-icons.css
zinnia_foundation/static/zinnia/icons/foundation-icons.eot
zinnia_foundation/static/zinnia/icons/foundation-icons.svg
zinnia_foundation/static/zinnia/icons/foundation-icons.ttf
zinnia_foundation/static/zinnia/icons/foundation-icons.woff
zinnia_foundation/static/zinnia/icons/preview.html
zinnia_foundation/static/zinnia/icons/svgs/fi-address-book.svg
zinnia_foundation/static/zinnia/icons/svgs/fi-alert.svg
zinnia_foundation/static/zinnia/icons/svgs/fi-align-center.svg
zinnia_foundation/static/zinnia/icons/svgs/fi-align-justify.svg
zinnia_foundation/static/zinnia/icons/svgs/fi-align-left.svg
zinnia_foundation/static/zinnia/icons/svgs/fi-align-right.svg
zinnia_foundation/static/zinnia/icons/svgs/fi-anchor.svg
zinnia_foundation/static/zinnia/icons/svgs/fi-annotate.svg
zinnia_foundation/static/zinnia/icons/svgs/fi-archive.svg
zinnia_foundation/static/zinnia/icons/svgs/fi-arrow-down.svg
zinnia_foundation/static/zinnia/icons/svgs/fi-arrow-left.svg
zinnia_foundation/static/zinnia/icons/svgs/fi-arrow-right.svg
zinnia_foundation/static/zinnia/icons/svgs/fi-arrow-up.svg
zinnia_foundation/static/zinnia/icons/svgs/fi-arrows-compress.svg
zinnia_foundation/static/zinnia/icons/svgs/fi-arrows-expand.svg
zinnia_foundation/static/zinnia/icons/svgs/fi-arrows-in.svg
zinnia_foundation/static/zinnia/icons/svgs/fi-arrows-out.svg
zinnia_foundation/static/zinnia/icons/svgs/fi-asl.svg
zinnia_foundation/static/zinnia/icons/svgs/fi-asterisk.svg
zinnia_foundation/static/zinnia/icons/svgs/fi-at-sign.svg
zinnia_foundation/static/zinnia/icons/svgs/fi-background-color.svg
zinnia_foundation/static/zinnia/icons/svgs/fi-battery-empty.svg
zinnia_theme_foundation.egg-info/PKG-INFO
zinnia_theme_foundation.egg-info/SOURCES.txt
zinnia_theme_foundation.egg-info/dependency_links.txt
zinnia_theme_foundation.egg-info/not-zip-safe
zinnia_theme_foundation.egg-info/top_level.txt