Metadata-Version: 1.1
Name: zinnia-theme-foundation
Version: 1.0.2
Summary: A theme with Zurb Foundation for django-blog-zinnia.
Home-page: https://github.com/django-blog-zinnia/zinnia-theme-foundation
Author: gustavi
Author-email: augustin.laville@gustavi.net
License: GPL
Keywords: django,blog,weblog,zinnia,theme,skin,foundation
Platform: UNKNOWN
Classifier: Framework :: Django
Classifier: Development Status :: 5 - Production/Stable
Classifier: Environment :: Web Environment
Classifier: Programming Language :: Python
Classifier: Programming Language :: Python :: 3
Classifier: Intended Audience :: Developers
Classifier: Operating System :: OS Independent
Classifier: License :: OSI Approved :: GNU General Public License v3 (GPLv3)
Classifier: Topic :: Software Development :: Libraries :: Python Modules
